txlib_too/__init__.py
txlib_too/_version.py
txlib_too/api/__init__.py
txlib_too/api/base.py
txlib_too/api/exceptions.py
txlib_too/api/project.py
txlib_too/api/resources.py
txlib_too/api/statistics.py
txlib_too/api/translations.py
txlib_too/api/tests/__init__.py
txlib_too/api/tests/test_base_model.py
txlib_too/api/tests/test_project.py
txlib_too/api/tests/test_resource.py
txlib_too/api/tests/test_statistics.py
txlib_too/api/tests/test_translation.py
txlib_too/api/tests/utils.py
txlib_too/http/__init__.py
txlib_too/http/auth.py
txlib_too/http/base.py
txlib_too/http/exceptions.py
txlib_too/http/http_requests.py
txlib_too/http/tests/__init__.py
txlib_too/http/tests/test_auth.py
txlib_too/http/tests/test_requests.py
txlib_too/registry/__init__.py
txlib_too/registry/registry.py
txlib_too/registry/tests/__init__.py
txlib_too/registry/tests/test_registry.py
txlib_too/tests/__init__.py
txlib_too/tests/compat.py
txlib_too/utils/__init__.py
txlib_too-0.1.8.dist-info/COPYING
txlib_too-0.1.8.dist-info/COPYING.LESSER
txlib_too-0.1.8.dist-info/METADATA
txlib_too-0.1.8.dist-info/WHEEL
txlib_too-0.1.8.dist-info/top_level.txt
txlib_too-0.1.8.dist-info/RECORD
