Metadata-Version: 2.1
Name: txlib-too
Version: 0.1.8
Summary: A python library for Transifex
Home-page: https://github.com/transifex/transifex-python-library
Author: eb-pypi
Author-email: eb-pypi@eventbrite.com
License: LGPL3
Keywords: translation,localization,internationalization
Platform: UNKNOWN
Classifier: Programming Language :: Python
Classifier: Programming Language :: Python :: 2
Classifier: Programming Language :: Python :: 2.7
Classifier: Programming Language :: Python :: 3
Classifier: Programming Language :: Python :: 3.4
Classifier: Programming Language :: Python :: 3.5
Requires-Dist: requests
Requires-Dist: six
